CHANGES.rst
MANIFEST.in
README.rst
setup.py
docs/Makefile
docs/collect.rst
docs/conf.py
docs/host.rst
docs/howto.rst
docs/index.rst
docs/intro.rst
docs/launcher.rst
docs/mixins.rst
docs/perf.rst
docs/plugin.rst
docs/response.rst
naghelp/__init__.py
naghelp/collect.py
naghelp/host.py
naghelp/launcher.py
naghelp/mixins.py
naghelp/perf.py
naghelp/plugin.py
naghelp/response.py
naghelp/tools.py
python_nagios_helpers3.egg-info/PKG-INFO
python_nagios_helpers3.egg-info/SOURCES.txt
python_nagios_helpers3.egg-info/dependency_links.txt
python_nagios_helpers3.egg-info/eager_resources.txt
python_nagios_helpers3.egg-info/not-zip-safe
python_nagios_helpers3.egg-info/requires.txt
python_nagios_helpers3.egg-info/top_level.txt
tests/db.json
tests/linux_fs_full_plugin.py
tests/plugin_common.py
tests/runtests.py