Metadata-Version: 1.1
Name: python-nagios-helpers3
Version: 0.2.2
Summary: Python3 helper Classes for plugin development and nagios management.
Home-page: https://github.com/elapouya/python-nagios-helpers
Author: Eric Lapouyade
Author-email: elapouya@gmail.com
License: LGPL 2.1
Keywords: naghelp
Platform: UNKNOWN
Classifier: Intended Audience :: Developers
Classifier: Development Status :: 4 - Beta
Classifier: Programming Language :: Python :: 3
